COPYING
shortuuid/__init__.py
shortuuid/cli.py
shortuuid/django_fields.py
shortuuid/main.py
shortuuid/test_shortuuid.py
shortuuid-1.0.10.dist-info/entry_points.txt
shortuuid-1.0.10.dist-info/COPYING
shortuuid-1.0.10.dist-info/WHEEL
shortuuid-1.0.10.dist-info/METADATA
shortuuid-1.0.10.dist-info/RECORD
